{
  "keys": {
    "my-key": {
      "public_key": [
        8,
        60,
        103,
        175,
        183,
        118,
        158,
        78,
        184,
        24,
        178,
        205,
        25,
        24,
        230,
        79,
        223,
        2,
        173,
        245,
        252,
        205,
        205,
        83,
        49,
        23,
        145,
        238,
        223,
        155,
        255,
        114
      ],
      "public_key_string": "CDxnr7d2nk64GLLNGRjmT98CrfX8zc1TMReR7t+b/3I=",
      "encrypted_secret_key": {
        "salt": [
          21,
          233,
          175,
          73,
          132,
          101,
          217,
          203,
          42,
          233,
          38,
          160,
          78,
          249,
          3,
          221,
          192,
          182,
          51,
          170,
          0,
          102,
          81,
          7,
          207,
          49,
          117,
          62,
          27,
          247,
          178,
          88
        ],
        "nonce": [
          19,
          121,
          198,
          13,
          216,
          148,
          196,
          209,
          157,
          151,
          141,
          50
        ],
        "encrypted_data": [
          43,
          72,
          124,
          98,
          141,
          67,
          176,
          0,
          65,
          200,
          203,
          224,
          184,
          56,
          186,
          60,
          33,
          56,
          212,
          218,
          252,
          135,
          92,
          78,
          58,
          5,
          7,
          239,
          224,
          217,
          12,
          95,
          8,
          253,
          92,
          247,
          149,
          245,
          168,
          167,
          16,
          173,
          194,
          173,
          174,
          56,
          150,
          195
        ]
      }
    }
  }
}